network_flow/.DS_Store
network_flow/.gitignore
network_flow/__init__.py
network_flow/main.py
network_flow/main_test.py
network_flow/.pytest_cache/.gitignore
network_flow/.pytest_cache/CACHEDIR.TAG
network_flow/.pytest_cache/README.md
network_flow/.pytest_cache/v/cache/lastfailed
network_flow/.pytest_cache/v/cache/nodeids
network_flow/.pytest_cache/v/cache/stepwise
network_flow/images/Presentation1.pptx
network_flow/images/img_01.png
network_flow/images/img_02.png
network_flow/images/img_03.png
network_flow/images/img_04.png
network_flow/images/img_05.png
network_flow/images/img_06.png
network_flow/images/img_07.png
network_flow/images/img_08.png
network_flow/images/img_09.png
network_flow/images/~$Presentation1.pptx
network_flow-0.0.2.dist-info/METADATA
network_flow-0.0.2.dist-info/WHEEL
network_flow-0.0.2.dist-info/licenses/LICENSE.txt
network_flow-0.0.2.dist-info/RECORD
