Metadata-Version: 2.1
Name: network_flow
Version: 0.0.2
Summary: Solve for unknown edge weights in a directed flow network.
Project-URL: Homepage, https://github.com/jajetloh/network_flow
Project-URL: Bug Tracker, https://github.com/jajetloh/network_flow/issues
Author-email: Ja-Jet Loh <jajet.codes@gmail.com>
License-File: LICENSE.txt
Classifier: License :: OSI Approved :: MIT License
Classifier: Operating System :: OS Independent
Classifier: Programming Language :: Python :: 3
Requires-Python: >=3.7
